[
  {
    "id": 1754740152537,
    "name": "Катя",
    "wishlist": [
      {
        "name": "2",
        "taken": false
      },
      {
        "name": "2",
        "taken": false
      },
      {
        "name": "2",
        "taken": false
      }
    ],
    "user_id": 1754739154746,
    "username": "Катя"
  },
  {
    "id": 1754740172260,
    "name": "Бажен",
    "wishlist": [
      {
        "name": "1",
        "taken": true
      },
      {
        "name": "1",
        "taken": true
      },
      {
        "name": "1",
        "taken": false
      },
      {
        "name": "1",
        "taken": false
      }
    ],
    "user_id": 1754739160412,
    "username": "Бажен"
  }
]